pyfastrand/__init__.py
pyfastrand/pcg32.py
pyfastrand/xorshift128plus.py
python_fastrand-1.1.dist-info/LICENSE
python_fastrand-1.1.dist-info/METADATA
python_fastrand-1.1.dist-info/WHEEL
python_fastrand-1.1.dist-info/top_level.txt
python_fastrand-1.1.dist-info/RECORD
