Metadata-Version: 2.1
Name: python-fastrand
Version: 1.1
Summary: Pure Python clone of fastrand
Home-page: https://github.com/mukundan314/python-fastrand.git
Author: Mukundan Senthil
Author-email: mukundan314@gmail.com
License: MIT
Keywords: random pcg
Platform: UNKNOWN
Classifier: Programming Language :: Python :: 2
Classifier: Programming Language :: Python :: 3
Classifier: Intended Audience :: Developers
Classifier: License :: OSI Approved :: MIT License
Classifier: Topic :: Software Development :: Libraries
